gito-2.0.dist-info/DESCRIPTION.rst
gito-2.0.dist-info/METADATA
gito-2.0.dist-info/RECORD
gito-2.0.dist-info/WHEEL
gito-2.0.dist-info/entry_points.txt
gito-2.0.dist-info/metadata.json
gito-2.0.dist-info/top_level.txt
src/__init__.py
src/config.py
src/data.py
src/date.py
src/exception.py
src/main.py
src/todo.py
src/util.py
src/validation.py
src/wunderlist.py
