Metadata-Version: 2.0
Name: gito
Version: 2.0
Summary: Tool to view list of Git TODO`s and sync with wunderlist
Home-page: https://github.com/raghu12133/gito
Author: raghu
Author-email: raghu12133@gmail.com
License: UNKNOWN
Platform: UNKNOWN
Classifier: Environment :: Console
Classifier: Intended Audience :: Developers
Requires-Dist: pathspec
Requires-Dist: pyyaml
Requires-Dist: requests
Requires-Dist: termcolor
